{"cameraMode":{"drawMode":0,"name":"Shaded","section":"Shading Mode"},"sceneLighting":false,"audioPlay":false,"sceneViewState":{"m_AlwaysRefresh":false,"showFog":true,"showSkybox":false,"showFlares":true,"showImageEffects":true,"showParticleSystems":true,"showVisualEffectGraphs":true,"m_FxEnabled":true},"in2DMode":false,"pivot":{"x":-1.9550001621246338,"y":0.875,"z":-2.935499906539917},"rotation":{"x":0.16457624733448029,"y":-0.6960066556930542,"z":0.16593630611896516,"w":0.6794122457504273},"size":5.7500224113464359,"orthographic":false}